setup.py
flaker/__init__.py
flaker/urllib2_file.py
flaker.egg-info/PKG-INFO
flaker.egg-info/SOURCES.txt
flaker.egg-info/dependency_links.txt
flaker.egg-info/requires.txt
flaker.egg-info/top_level.txt
flaker.egg-info/zip-safe