Metadata-Version: 1.0
Name: flaker
Version: 0.2.5
Summary: Flaker.pl client
Home-page: http://github.com/ryszard/python-flaker/
Author: Ryszard Szopa
Author-email: ryszard.szopa@gmail.com
License: MIT
Keywords: internet flaker api
Platform: UNKNOWN
Classifier: License :: OSI Approved :: MIT License
Classifier: Programming Language :: Python
Classifier: Operating System :: OS Independent
Classifier: Development Status :: 3 - Alpha
Classifier: Intended Audience :: Developers
Classifier: Topic :: Internet
